{
    "productos": [
        {
            "id": 1,
            "nombre": "Criollo con base",
            "precio": 14000,
            "imagen": "./img/img-producto-id1/criollo-1.webp",
            "fotosExtras": ["./img/img-producto-id1/criolloPersonalizado-1.webp","./img/img-producto-id1/criolloPersonalizado-2.webp"],
            "descripcion": "Mate criollo calabaza pulida con base de cuero crudo cocido",
            "tipos": ["mate"],
            "aptoParaGrabado": false,
            "stock": 3,
            "colores": [
                { "nombre": "Verde", "hex": "#2d5d52", "disponible": true },
                { "nombre": "Negro", "hex": "#222", "disponible": true },
                { "nombre": "Rojo", "hex": "#c0392b", "disponible": false }
            ]
        },
        {
            "id": 2,
            "nombre": "Criollo Premium virola de alpaca cincelada",
            "precio": 28000,
            "imagen": "./img/img-producto-id2/criolloPremium-1.webp",
            "fotosExtras": ["./img/img-producto-id2/criolloPremium-2.webp"],
            "descripcion": "Mate criollo con base de cuero crudo cocido, virola de alpaca cincelada",
            "tipos": ["mate"],
            "aptoParaGrabado": false,
            "stock": 2,
            "colores": [
                { "nombre": "Marrón y Negro", "hex": ["#8B5C2A", "#222"], "disponible": true },
                { "nombre": "Marrón", "hex": "#8B5C2A", "disponible": false }
            ]
        },
        
        {
            "id": 4,
            "nombre": "Camionero de algarrobo virola de acero inox lisa",
            "precio": 16000,
            "imagen": "./img/img-producto-id4/camioneroAlgarrobo-3.webp",
            "fotosExtras": ["./img/img-producto-id4/camioneroAlgarrobo-2.webp","./img/img-producto-id4/camioneroDeAlgarrobo-1.webp"],
            "descripcion": "Mate camionero de algarrobo con virola lisa de acero inoxidable",
            "tipos": ["mate"],
            "aptoParaGrabado": true,
            "stock": 0
        },
        {
            "id": 5,
            "nombre": "Imperial de algarrobo virola de alpaca lisa",
            "precio": 26000,
            "imagen": "./img/img-producto-id5/imperialAlgarrobo-3.webp",
            "fotosExtras": ["./img/img-producto-id5/imperialAlgarrobo-1.webp","./img/img-producto-id5/imperialAlgarrobo-2.webp","./img/img-producto-id5/imperialAlgarroboPersonalizado-1.webp"],
            "descripcion": "Mate imperial de algarrobo con virola lisa y guarda de alpaca",
            "tipos": ["mate"],
            "aptoParaGrabado": true,
            "stock": 0
        },
        {
            "id": 6,
            "nombre": "Torpedo virola de acero inox lisa",
            "precio": 24000,
            "imagen": "./img/img-producto-id6/torpedoAceroLiso-3.webp",
            "fotosExtras": ["./img/img-producto-id6/torpedoAceroLiso-2.webp","./img/img-producto-id6/torpedoAceroLiso-1.webp"],
            "descripcion": "Mate torpedo de calabaza exterior de cuero reforzado con virola de acero inoxidable lisa",
            "tipos": ["mate"],
            "aptoParaGrabado": false,
            "stock": 1
        },
        {
            "id": 7,
            "nombre": "Torpedo virola cincelada de alpaca",
            "precio": 28000,
            "imagen": "./img/img-producto-id7/TorpedoAlpacaCincelado-1.webp",
            "fotosExtras": ["./img/img-producto-id7/torpedoAlpacaCincelado-2.webp"],
            "descripcion": "Mate torpedo de calabaza exterior de cuero reforzado con virola de alpaca cincelada",
            "tipos": ["mate"],
            "aptoParaGrabado": false,
            "stock": 0
        },
        {
            "id": 8,
            "nombre": "Torpedo virola cincelada y base con bolitas de alpaca",
            "precio": 32000,
            "imagen": "./img/img-producto-id8/torpedoAlpacaCinceladoYBolitas-1.webp",
            "fotosExtras": [],
            "descripcion": "Mate torpedo de calabaza exterior de cuero reforzado con virola cincelada, base y bolitas de alpaca",
            "tipos": ["mate"],
            "aptoParaGrabado": false,
            "stock": 0
        },
        {
            "id": 9,
            "nombre": "Camionero virola de acero inox lisa con cuero labrado",
            "precio": 22000,
            "imagen": "./img/img-producto-id9/camioneroAceroLisoLabrado-1.webp",
            "fotosExtras": [],
            "descripcion": "Mate camionero de calabaza exterior de cuero reforzado, labrado y con virola de acero inoxidable lisa",
            "tipos": ["mate"],
            "aptoParaGrabado": true,
            "stock": 0
        },
        {
            "id": 10,
            "nombre": "Camionero virola de acero inox lisa",
            "precio": 24000,
            "imagen": "./img/img-producto-id10/camioneroLiso-2.webp",
            "fotosExtras": ["./img/img-producto-id10/matepas-1_camionerosLisos-2.webp", "./img/img-producto-id10/camioneroPersonalizado-1.webp"],
            "descripcion": "Mate camionero de calabaza con exterior de cuero reforzado y virola de acero inoxidable",
            "tipos": ["mate"],
            "aptoParaGrabado": true,
            "stock": 0
        },
        {
            "id": 11,
            "nombre": "Imperial virola de alpaca lisa",
            "precio": 32000,
            "imagen": "./img/img-producto-id11/imperialLiso-3.webp",
            "fotosExtras": ["./img/img-producto-id11/imperialLisoPersonalizado-2.webp","./img/img-producto-id11/imperialLisoPersonalizado-3.webp","./img/img-producto-id11/imperialLiso-2.webp","./img/img-producto-id11/imperialLiso-1.webp"],
            "descripcion": "",
            "tipos": ["mate"],
            "aptoParaGrabado": true,
            "stock": 3
        },
        {
            "id": 12,
            "nombre": "Imperial virola de alpaca cincelada",
            "precio": 35000,
            "imagen": "./img/img-producto-id12/imperialCincelado-2.webp",
            "fotosExtras": ["./img/img-producto-id12/imperialCincelado-1.webp","./img/img-producto-id12/imperialCincelado-3.webp"],
            "descripcion": "",
            "tipos": ["mate"],
            "aptoParaGrabado": false,
            "stock": 1
        },
        {
            "id": 13,
            "nombre": "Imperial criollo con cuero labrado",
            "precio": 50000,
            "imagen": "./img/img-producto-id13/imperialCriollo-1.webp",
            "fotosExtras": ["./img/img-producto-id13/imperialCriollo-2.webp"],
            "descripcion": "",
            "tipos": ["mate"],
            "aptoParaGrabado": true,
            "stock": 1
        },
        {
            "id": 14,
            "nombre": "Bombilla Pico de Loro de acero inox",
            "precio": 7000,
            "imagen": "./img/img-producto-id14/bombillasAceroInox-1.webp",
            "fotosExtras": ["./img/img-producto-id14/bombillasAceroInox-2.webp","./img/img-producto-id14/bombillaPicoLoroAceroInox-3.webp"],
            "descripcion": "Bombilla de alpaca con pico de loro",
            "tipos": ["bombilla"],
            "aptoParaGrabado": false,
            "stock": 5,
            "colores": []
        },
        {
            "id": 15,
            "nombre": "Bombilla de acero inox chata",
            "precio": 5000,
            "imagen": "./img/img-producto-id15/bombillaChataAceroInox-3.webp",
            "fotosExtras": ["./img/img-producto-id15/bombillaChataAceroInox-1.webp","./img/img-producto-id15/bombillaChataAceroInox-2.webp"],
            "descripcion": "",
            "tipos": ["bombilla"],
            "aptoParaGrabado": false,
            "stock": 4
        },
        {
            "id": 16,
            "nombre": "Bombilla pico de loro de alpaca",
            "precio": 12000,
            "imagen": "",
            "fotosExtras": [],
            "descripcion": "NO TENGO FOTO",
            "tipos": ["bombilla"],
            "aptoParaGrabado": false,
            "stock": 3
        },
        {
            "id": 17,
            "nombre": "Bombillón de alpaca",
            "precio": 22000,
            "imagen": "./img/img-producto-id17/bombillonAlpaca-1.webp",
            "fotosExtras": ["./img/img-producto-id17/bombillon-4.webp", "./img/img-producto-id17/bombillon-5.webp", "./img/img-producto-id17/bombillon-6.webp","./img/img-producto-id17/bombillon-2_criollo-2.webp"],
            "descripcion": "",
            "tipos": ["bombilla"],
            "aptoParaGrabado": false,
            "stock": 0
        },
        {
            "id": 18,
            "nombre": "Bombillón de alpaca premium",
            "precio": 26000,
            "imagen": "./img/img-producto-id18/bombillonPremium-1.webp",
            "fotosExtras": [],
            "descripcion": "",
            "tipos": ["bombilla"],
            "aptoParaGrabado": false,
            "stock": 0
        },
        {
            "id": 19,
            "nombre": "Yerbera de gamuza",
            "precio": 7000,
            "imagen": "./img/img-producto-id19/yerberoGamuzaNegro-1.webp",
            "fotosExtras": ["./img/img-producto-id19/yerberoGamuzaNegro-2.webp"],
            "descripcion": "Yerbera de cuero con diseño artesanal",
            "tipos": ["accesorio"],
            "aptoParaGrabado": false,
            "stock": 6,
            "colores": [
                { "nombre": "Blanco y Negro", "hex": ["#fff", "#222"], "disponible": true },
                { "nombre": "Negro", "hex": "#222", "disponible": true }
            ]
        },
        {
            "id": 20,
            "nombre": "Yerbero de gamuza con bolsillo",
            "precio": 12000,
            "imagen": "./img/img-producto-id20/yerberoGamuzaBolsillo-1.webp",
            "fotosExtras": ["./img/img-producto-id20/yerberoGamuzaBolsillo-2.webp",
            "./img/img-producto-id20/yerberoGamuzaBolsillo-3.webp",
            "./img/img-producto-id20/yerberoGamuzaBolsillo-4.webp",
            "./img/img-producto-id20/yerberoGamuzaBolsillo-5.webp",
            "./img/img-producto-id20/yerberoGamuzaBolsillo-6.webp"],
            "descripcion": "",
            "tipos": ["accesorio"],
            "aptoParaGrabado": false,
            "stock": 4
        },
        {
            "id": 21,
            "nombre": "Canasta de ecocuero",
            "precio": 9000,
            "imagen": "./img/img-producto-id21/CanastaEcocuero.webp",
            "fotosExtras": [],
            "descripcion": "",
            "tipos": ["accesorio"],
            "aptoParaGrabado": false,
            "stock": 3
        },
        {
            "id": 22,
            "nombre": "Canasta de ecocuero reforzada",
            "precio": 15000,
            "imagen": "./img/img-producto-id22/CanastaEcocueroReforzada.webp",
            "fotosExtras": [],
            "descripcion": "",
            "tipos": ["accesorio"],
            "aptoParaGrabado": false,
            "stock": 5
        },
        {
            "id": 23,
            "nombre": "Canasta de cuero 100%",
            "precio": 35000,
            "imagen": "./img/img-producto-id23/canastaCuero-2.webp",
            "fotosExtras": ["./img/img-producto-id23/canastaCuero-1.webp", "./img/img-producto-id23/canastaCuero-3.webp","./img/img-producto-id23/canastaCuero-4.webp"],
            "descripcion": "",
            "tipos": ["accesorio"],
            "aptoParaGrabado": false,
            "stock": 2
        },
        {
            "id": 24,
            "nombre": "TapaMate de silicona",
            "precio": 10000,
            "imagen": "./img/img-producto-id24/tapamate-3.webp",
            "fotosExtras": ["./img/img-producto-id24/tapamate-6.webp", "./img/img-producto-id24/tapamate-5.webp", "./img/img-producto-id24/tapamate-4.webp", "./img/img-producto-id24/tapamate-2.webp"],
            "descripcion": "",
            "tipos": ["accesorio"],
            "aptoParaGrabado": false,
            "stock": 5
        },
        {
            "id": 25,
            "nombre": "TapaBombi de silicona",
            "precio": 6000,
            "imagen": "./img/img-producto-id25/Tapabombi.webp",
            "fotosExtras": ["./img/img-producto-id25/Tapabombi-2.webp"],
            "descripcion": "",
            "tipos": ["accesorio"],
            "aptoParaGrabado": false,
            "stock": 5
        },
        {
            "id": 26,
            "nombre": "Portamate de cuero 100%",
            "precio": 14000,
            "imagen": "./img/img-producto-id26/portamate-1.webp",
            "fotosExtras": ["./img/img-producto-id26/portamate-2.webp"],
            "descripcion": "",
            "tipos": ["accesorio"],
            "aptoParaGrabado": false,
            "stock": 0
        }
    ]
} 